ssh2awsec2/__init__.py
ssh2awsec2/_version.py
ssh2awsec2/api.py
ssh2awsec2/better_boto.py
ssh2awsec2/boto_ses.py
ssh2awsec2/cache.py
ssh2awsec2/config.py
ssh2awsec2/logger.py
ssh2awsec2/paths.py
ssh2awsec2/pem_file.py
ssh2awsec2/recent.py
ssh2awsec2/cli/__init__.py
ssh2awsec2/cli/commands.py
ssh2awsec2/cli/config.py
ssh2awsec2/cli/main.py
ssh2awsec2/cli/ssh.py
ssh2awsec2/docs/__init__.py
ssh2awsec2/tests/__init__.py
ssh2awsec2/tests/helper.py
ssh2awsec2/vendor/__init__.py
ssh2awsec2/vendor/pytest_cov_helper.py
ssh2awsec2/vendor/vislog/__init__.py
ssh2awsec2/vendor/vislog/_version.py
ssh2awsec2/vendor/vislog/impl.py
ssh2awsec2-0.1.2.dist-info/AUTHORS.rst
ssh2awsec2-0.1.2.dist-info/LICENSE.txt
ssh2awsec2-0.1.2.dist-info/METADATA
ssh2awsec2-0.1.2.dist-info/WHEEL
ssh2awsec2-0.1.2.dist-info/entry_points.txt
ssh2awsec2-0.1.2.dist-info/top_level.txt
ssh2awsec2-0.1.2.dist-info/RECORD
